<?xml version="1.0" encoding="UTF-8" standalone="yes"?>
<?xml-stylesheet type='text/xsl' href='../viewxml.xsl'?>
<DOC>
  <navn>Solbærsorbet</navn>
  <ingredienser>
    <ing>1 dl. vand</ing>
    <ing>1 dl. sukker (evt 1/3 brun farin)</ing>
    <ing>3 dl. friske solbær</ing>
    <ing>2 æggehvider, pasteuriseret</ing>
    <ing>1 spsk. flormelis</ing>
    <ing>(evt. 80 g chokoladespåner, 70 % kakaoindhold)</ing>
  </ingredienser>
  <metode>
    <met>Kog vand, sukker og 1 dl bær i 5 minutter. Når det har kogt, tilsættes resten af bærrene. Blandingen svales, blendes og pureres gennem en sigte.</met>
    <met>Frys blandingen ca. 1½ time, indtil massen har konsistens som softice (rør evt. hver halve time). Pisk nu æggehvider stive med flormelis. Vend det i isen, evt. sammen med chokospåner.</met>
    <met>Frys igen ½ time og rør op igen. Stilles atter i fryseren mindst 1½ - 2 timer.</met>
    <met>Sorbeten kan serveres med solbærlikør og chokoladekage.</met>
  </metode>
</DOC>
